{
	"id":"testSelect",
	"type":"combinationSelect",
	"description":"",
	"content":{
		"resultSet":[
			{
				"columnName":"nike_name",
				"columnFunction":{
					"name":"",
					"parameters":[]
				},
				"alias":"昵称"
			}
		],
		"table":{
			"type":"table",
			"name":"sys_user",
			"subSqlId":"",
			"subSqlJson":{

			},
			"alias":""
		},
		"join":[
			{
				"type":"inner",
				"tableType":"table",
				"tableName":"sys_user",
				"alias":"u",
				"on":[
					{
						"onGroup":[
							{
								"leftColumnName":"name",
								"leftFunction":{
									"name":"",
									"parameters":[]
								},
								"operator":"eq",
								"rightColumnName":"nike_name",
								"rightFunction":{
									"name":"",
									"parameters":[]
								},
								"nextLogicOperator":"and"
							},
							{
								"leftColumnName":"name",
								"leftFunction":{
									"name":"",
									"parameters":[]
								},
								"operator":"eq",
								"rightColumnName":"nike_name",
								"rightFunction":{
									"name":"",
									"parameters":[]
								},
								"nextLogicOperator":"and"
							}
						],
						"nextLogicOperator":"and"
					}
				]
			}
		],
		"where":[
			{
				"whereGroup":[
					{
						"columnName":"nike_name",
						"columnFunction":{
							"name":"",
							"parameters":[]
						},
						"operator":"eq",
						"value":{
							"type":"value",
							"value":["d"],
							"valueFunction": [
								{
									"name": "to_char",
									"parameters": ["'test'", "varchar2(20)"]
								}
							],
							"subSqlId": "",
							"subSqlJson": {
							}
						},
						"nextLogicOperator":"and"
					}
				],
				"nextLogicOperator":"and"
			}
		],
		"groupBy":[
			{
				"columnName":"nike_name",
				"columnFunction":{
					"name":"",
					"parameters":[]
				}
			}
		],
		"having":[
			{
				"havingGroup":[
					{
						"columnName":"nike_name",
						"columnFunction":{
							"name":"",
							"parameters":[]
						},
						"operator":"eq",
						"value":{
							"type":"value",
							"value":["d"],
							"valueFunction": [
								{
									"name": "to_char",
									"parameters": ["'test'", "varchar2(20)"]
								}
							],
							"subSqlId": "",
							"subSqlJson": {
							}
						},
						"nextLogicOperator":"and"
					}
				],
				"nextLogicOperator":"and"
			}
		],
		"orderBy":[
			{
				"columnName":"nike_name",
				"columnFunction":{
					"name":"",
					"parameters":[]
				},
				"sort":"asc"
			}
		]
	}
}